necroplankton/__init__.py
necroplankton-0.0.2.dist-info/DESCRIPTION.rst
necroplankton-0.0.2.dist-info/METADATA
necroplankton-0.0.2.dist-info/RECORD
necroplankton-0.0.2.dist-info/WHEEL
necroplankton-0.0.2.dist-info/metadata.json
necroplankton-0.0.2.dist-info/top_level.txt
