Metadata-Version: 2.0
Name: necroplankton
Version: 0.0.2
Summary: tool set
Home-page: UNKNOWN
Author: necroplankton
Author-email: necroplankton@rainy.me
License: MIT Licence
Platform: UNKNOWN
Classifier: Development Status :: 4 - Beta
Classifier: Intended Audience :: Developers
Classifier: Programming Language :: Python :: 3.6
Requires-Python: >=3.6
Requires-Dist: requests
